 

{
	"list1":[{
		"bigimg_src":"list_page_1.jpg",
		"smallimg_src":"list_small_1.jpg",
		"title":"顽皮Wanpy 奶酪小馒头 220g",
		"oldprice":"¥14.40",
		"price":"¥12.00",
		"data_id":"0039"
	},{
		"bigimg_src":"list_page_6.jpg",
		"smallimg_src":"list_small_6.jpg",
		"title":"顽皮Wanpy 奶酪小馒头 300g",
		"oldprice":"¥19.80",
		"price":"¥15.00",
		"data_id":"0040"	
	},{
		"bigimg_src":"list_page_3.jpg",
		"smallimg_src":"list_small_3.jpg",
		"title":"顽皮Wanpy 奶酪小馒头 400g",
		"oldprice":"¥22.90",
		"price":"¥19.00",
		"data_id":"0041"
	}],
	"list2":[{
		"bigimg_src":"list_page_4.jpg",
		"smallimg_src":	"list_small_4.jpg",						
		"title":"爱丽丝 IRIS 芝士小馒头 220g",
		"oldprice":"¥27.00",
		"price":"¥26.00",
		"data_id":"0042"
	},{
		"bigimg_src":"list_page_5.jpg",
		"smallimg_src":	"list_small_5.jpg",		
		"title":"爱丽丝 IRIS 芝士小馒头 360g",
		"oldprice":"¥40.80",
		"price":"¥36.00",
		"data_id":"0043"	
	},{
		"bigimg_src":"list_page_7.jpg",
		"smallimg_src":	"list_small_7.jpg",		
		"title":"哈格米奇除臭小饼干 300g",
		"oldprice":"¥19.80",
		"price":"¥15.00",
		"data_id":"0045"	
	},{
		"bigimg_src":"list_page_9.jpg",
		"smallimg_src":	"list_small_9.jpg",		
		"title":"哈格米奇除臭小饼干 200g",
		"oldprice":"¥16.80",
		"price":"¥15.00",
		"data_id":"0082"	
	}],
	"list3":[{
		"bigimg_src":"list_page_6.jpg",
		"smallimg_src":	"list_small_6.jpg",						
		"title":"哈格米奇除臭小饼干 220g",
		"oldprice":"¥14.40",
		"price":"¥12.00",
		"data_id":"0081"
	},{
		"bigimg_src":"list_page_7.jpg",
		"smallimg_src":	"list_small_7.jpg",		
		"title":"哈格米奇除臭小饼干 300g",
		"oldprice":"¥19.80",
		"price":"¥15.00",
		"data_id":"0080"	
	},{
		"bigimg_src":"list_page_9.jpg",
		"smallimg_src":	"list_small_9.jpg",						
		"title":"博客新 雪花牛肉饼干 290g",
		"oldprice":"¥24.40",
		"price":"¥17.00",
		"data_id":"0091"
	}],	
	"list4":[{
		"bigimg_src":"list_page_8.jpg",
		"smallimg_src":	"list_small_8.jpg",						
		"title":"牛肉小馒头狗零食 220g",
		"oldprice":"¥14.40",
		"price":"¥12.00",
		"data_id":"0046"
	},{
		"bigimg_src":"list_page_7.jpg",
		"smallimg_src":	"list_small_7.jpg",		
		"title":"牛肉小馒头狗零食 300g",
		"oldprice":"¥19.80",
		"price":"¥15.00",
		"data_id":"0047"	
	},{
		"bigimg_src":"list_page_8.jpg",
		"smallimg_src":	"list_small_8.jpg",		
		"title":"牛肉小馒头狗零食 440g",
		"oldprice":"¥28.80",
		"price":"¥10.00",
		"data_id":"0048"	
	}],
	"list5":[{
		"bigimg_src":"list_page_9.jpg",
		"smallimg_src":	"list_small_9.jpg",						
		"title":"博客新 雪花牛肉饼干 290g",
		"oldprice":"¥24.40",
		"price":"¥17.00",
		"data_id":"0049"
	},{
		"bigimg_src":"list_page_10.jpg",
		"smallimg_src":	"list_small_10.jpg",		
		"title":"博客新 雪花牛肉饼干 380g",
		"oldprice":"¥39.80",
		"price":"¥15.80",
		"data_id":"0050"	
	},{
		"bigimg_src":"list_page_8.jpg",
		"smallimg_src":	"list_small_8.jpg",		
		"title":"博客新 雪花牛肉饼干 450g",
		"oldprice":"¥18.80",
		"price":"¥10.00",
		"data_id":"0051"	
	}],
	"list6":[{
		"bigimg_src":"list_page_10.jpg",
		"smallimg_src":	"list_small_10.jpg",						
		"title":"博客新 雪花牛肉饼干 990g",
		"oldprice":"¥124.40",
		"price":"¥137.00",
		"data_id":"0052"	
	},{
		"bigimg_src":"list_page_10.jpg",
		"smallimg_src":	"list_small_10.jpg",		
		"title":"博客新 雪花牛肉饼干 380g",
		"oldprice":"¥39.80",
		"price":"¥15.80",
		"data_id":"0090"	
	}],
	"list7":[{
		"bigimg_src":"list_page_12.jpg",
		"smallimg_src":	"list_small_12.jpg",						
		"title":"博客新 圈圈饼干狗 90g",
		"oldprice":"¥54.40",
		"price":"¥47.00",
		"data_id":"0053"	
	},{
		"bigimg_src":"list_page_10.jpg",
		"smallimg_src":	"list_small_10.jpg",		
		"title":"博客新 雪花牛肉饼干 380g",
		"oldprice":"¥39.80",
		"price":"¥15.80",
		"data_id":"0089"	
	}],
	"list8":[{
		"bigimg_src":"list_page_9.jpg",
		"smallimg_src":	"list_small_9.jpg",						
		"title":"露丝粗粮系列 190g",
		"oldprice":"¥34.40",
		"price":"¥27.00",
		"data_id":"0054"	
	}],	
	"list9":[{
		"bigimg_src":"list_page_18.jpg",
		"smallimg_src":	"list_small_18.jpg",						
		"title":"牛肉小馒头狗零食 220g",
		"oldprice":"¥14.40",
		"price":"¥12.00",
		"data_id":"0055"
	},{
		"bigimg_src":"list_page_17.jpg",
		"smallimg_src":	"list_small_17.jpg",		
		"title":"牛肉小馒头狗零食 300g",
		"oldprice":"¥19.80",
		"price":"¥15.00",
		"data_id":"0056"	
	},{
		"bigimg_src":"list_page_19.jpg",
		"smallimg_src":	"list_small_19.jpg",		
		"title":"牛肉小馒头狗零食 400g",
		"oldprice":"¥18.80",
		"price":"¥10.00",
		"data_id":"0057"	
	},{
		"bigimg_src":"list_page_20.jpg",
		"smallimg_src":	"list_small_20.jpg",		
		"title":"牛肉小馒头狗零食 400g",
		"oldprice":"¥18.80",
		"price":"¥10.00",
		"data_id":"0058"
	},{
		"bigimg_src":"list_page_10.jpg",
		"smallimg_src":	"list_small_10.jpg",		
		"title":"博客新 雪花牛肉饼干 380g",
		"oldprice":"¥39.80",
		"price":"¥15.80",
		"data_id":"0088"	
	}],
	"list10":[{
		"bigimg_src":"list_page_10.jpg",
		"smallimg_src":	"list_small_10.jpg",						
		"title":"牛肉小馒头狗零食 220g",
		"oldprice":"¥12.40",
		"price":"¥19.00",
		"data_id":"0059"
	},{
		"bigimg_src":"list_page_9.jpg",
		"smallimg_src":	"list_small_9.jpg",		
		"title":"牛肉小馒头狗零食 300g",
		"oldprice":"¥19.80",
		"price":"¥15.00",
		"data_id":"0060"	
	},{
		"bigimg_src":"list_page_8.jpg",
		"smallimg_src":	"list_small_8.jpg",		
		"title":"牛肉小馒头狗零食 400g",
		"oldprice":"¥28.80",
		"price":"¥19.40",
		"data_id":"0061"	
	},{
		"bigimg_src":"list_page_3.jpg",
		"smallimg_src":	"list_small_3.jpg",		
		"title":"牛肉小馒头狗零食 400g",
		"oldprice":"¥18.80",
		"price":"¥10.00",
		"data_id":"0062"
	}],
	"list11":[{
		"bigimg_src":"list_page_4.jpg",
		"smallimg_src":	"list_small_4.jpg",						
		"title":"爱丽丝 IRIS 芝士小馒头 220g",
		"oldprice":"¥27.00",
		"price":"¥26.00",
		"data_id":"0063"
	},{
		"bigimg_src":"list_page_5.jpg",
		"smallimg_src":	"list_small_5.jpg",		
		"title":"爱丽丝 IRIS 芝士小馒头 360g",
		"oldprice":"¥40.80",
		"price":"¥36.00",
		"data_id":"0064"	
	}],
	"list12":[{
		"bigimg_src":"list_page_9.jpg",
		"smallimg_src":	"list_small_9.jpg",						
		"title":"爱丽丝 IRIS 芝士小馒头 220g",
		"oldprice":"¥27.00",
		"price":"¥26.00",
		"data_id":"0065"
	},{
		"bigimg_src":"list_page_3.jpg",
		"smallimg_src":	"list_small_3.jpg",		
		"title":"爱丽丝 IRIS 芝士小馒头 360g",
		"oldprice":"¥40.80",
		"price":"¥36.00",
		"data_id":"0066"	
	}]	
}
